scripts/__init__.py
scripts/mmtests.py
scripts/squad_get.py
squad_report/__init__.py
squad_report/cli.py
squad_report/config.py
squad_report/dataframe.py
squad_report/datasets.py
squad_report/logging.py
squad_report/reports.py
squad_report/version.py
squad_report/templates/build.txt.jinja
squad_report/templates/perf-report.txt.jinja
squad_report/templates/report-full.txt.jinja
squad_report/templates/report.txt.jinja
squad_report/templates/blocks/base.jinja
squad_report/templates/blocks/fails.jinja
squad_report/templates/blocks/kernel.jinja
squad_report/templates/blocks/signature.jinja
squad_report/templates/blocks/subject.jinja
squad_report/templates/blocks/summary.jinja
squad_report-1.9.0.dist-info/LICENSE
squad_report-1.9.0.dist-info/METADATA
squad_report-1.9.0.dist-info/WHEEL
squad_report-1.9.0.dist-info/entry_points.txt
squad_report-1.9.0.dist-info/top_level.txt
squad_report-1.9.0.dist-info/RECORD
