Metadata-Version: 2.1
Name: squad-report
Version: 1.9.0
Summary: Create human-friendly reports from software quality data
Home-page: https://gitlab.com/linaro/lkft/reports/squad-report
Author: LKFT
Author-email: lkft@linaro.org
License: MIT
Platform: UNKNOWN
Requires-Python: >=3.6, <4
License-File: LICENSE
Requires-Dist: jinja2
Requires-Dist: pandas
Requires-Dist: requests
Requires-Dist: pyyaml
Requires-Dist: squad-client (>=0.22)
